axe_selenium_python/__init__.py
axe_selenium_python/axe.py
axe_selenium_python/node_modules/axe-core/axe.min.js
axe_selenium_python/tests/__init__.py
axe_selenium_python/tests/conftest.py
axe_selenium_python/tests/test_axe.py
axe_selenium_python/tests/test_page.html
axe_selenium_python_nhsuk-1.0.4.dist-info/LICENSE.txt
axe_selenium_python_nhsuk-1.0.4.dist-info/METADATA
axe_selenium_python_nhsuk-1.0.4.dist-info/WHEEL
axe_selenium_python_nhsuk-1.0.4.dist-info/top_level.txt
axe_selenium_python_nhsuk-1.0.4.dist-info/RECORD
