Metadata-Version: 2.1
Name: axe-selenium-python-nhsuk
Version: 1.0.4
Summary: Python library to integrate axe and selenium for web                 accessibility testing.
Home-page: https://github.com/ghufrankhan/axe-selenium-python
License: Mozilla Public License 2.0 (MPL 2.0)
Keywords: axe-core axe python selenium accessibility testing automation
License-File: LICENSE.txt
Requires-Dist: selenium>=4.0.0
